macrometa_source_mongo/__init__.py
macrometa_source_mongo/connection.py
macrometa_source_mongo/exceptions.py
macrometa_source_mongo/helper.py
macrometa_source_mongo/sync_strategies/common.py
macrometa_source_mongo/sync_strategies/full_table.py
macrometa_source_mongo/sync_strategies/log_based.py
macrometa_source_mongo/sync_strategies/sample_data.py
macrometa_source_mongo-1.0.0.dist-info/entry_points.txt
macrometa_source_mongo-1.0.0.dist-info/LICENSE
macrometa_source_mongo-1.0.0.dist-info/WHEEL
macrometa_source_mongo-1.0.0.dist-info/METADATA
macrometa_source_mongo-1.0.0.dist-info/RECORD
